{
    "id": "565752",
    "meta": {
        "lastUpdated": "2020-09-15T22:01:09.521-04:00",
        "versionId": "1"
    },
    "identifier": [
        {
            "assigner": {
                "display": "United States of America"
            },
            "period": {
                "end": "2024-12-04"
            },
            "type": {
                "coding": [
                    {
                        "code": "PPN",
                        "display": "Passport Number",
                        "system": "http://terminology.hl7.org/CodeSystem/v2-0203"
                    }
                ]
            },
            "value": "12345678-90"
        }
    ],
    "name": [
        {
            "family": [
                "Patient"
            ],
            "given": [
                "Lab A"
            ]
        }
    ],
    "resourceType": "Patient"
}